{
  "resource": "Articles",
  "resource_explanation": "Articles Resource",
  "http_method": "PATCH",
  "route": "api/v1/articles/:id/love.json",
  "description": "Loving Article By ID",
  "explanation": null,
  "parameters": [

  ],
  "response_fields": [

  ],
  "requests": [
    {
      "request_method": "PATCH",
      "request_path": "api/v1/articles/71/love.json",
      "request_body": null,
      "request_headers": {
        "Host": "example.org",
        "Content-Type": "application/x-www-form-urlencoded",
        "Cookie": ""
      },
      "request_query_parameters": {
      },
      "request_content_type": "application/x-www-form-urlencoded",
      "response_status": 200,
      "response_status_text": "OK",
      "response_body": "{\n  \"id\": 71,\n  \"name\": \"Jesse Runolfsson\",\n  \"is_published\": true,\n  \"publish_date\": \"2009-09-14T08:00:00.000Z\",\n  \"likes\": 0,\n  \"loves\": 1,\n  \"author\": {\n    \"id\": 71,\n    \"name\": \"Wallace Bogan\",\n    \"email\": \"candyce_feil@koepp.name\",\n    \"image\": \"path-to-image\"\n  }\n}",
      "response_headers": {
        "Content-Type": "application/json; charset=utf-8",
        "ETag": "W/\"e42dda138134c28bb287e94643dbf5cf\"",
        "Cache-Control": "max-age=0, private, must-revalidate",
        "X-Request-Id": "745bd858-f01a-4bea-ad59-f322ea9589d0",
        "X-Runtime": "0.009304",
        "Content-Length": "217"
      },
      "response_content_type": "application/json; charset=utf-8",
      "curl": null
    }
  ]
}